neurojit/commit.py
neurojit/cuf/__init__.py
neurojit/cuf/cfg.py
neurojit/cuf/halstead.py
neurojit/cuf/metrics.py
neurojit/cuf/rii.py
neurojit/tools/__init__.py
neurojit/tools/data_utils.py
neurojit-1.0.2.dist-info/METADATA
neurojit-1.0.2.dist-info/WHEEL
neurojit-1.0.2.dist-info/entry_points.txt
neurojit-1.0.2.dist-info/licenses/LICENSE
neurojit-1.0.2.dist-info/RECORD
