Metadata-Version: 2.3
Name: neurojit
Version: 1.0.2
Summary: A Python package for calculating the commit understandability features of Java projects.
Project-URL: homepage, https://github.com/Verssae/NeuroJIT
Project-URL: repository, https://github.com/Verssae/NeuroJIT
Project-URL: bug_tracker, https://github.com/Verssae/NeuroJIT/issues
Author-email: Hansae Ju <sparky@hanyang.ac.kr>
Maintainer-email: Hansae Ju <sparky@hanyang.ac.kr>
License:                                  Apache License
License-File: LICENSE
Requires-Python: >=3.11
Requires-Dist: javalang>=0.13.0
Requires-Dist: numpy>=1.26.4
Requires-Dist: pandas>=2.2.1
Requires-Dist: pydriller>=2.6
Provides-Extra: replication
Requires-Dist: cliffs-delta>=1.0.0; extra == 'replication'
Requires-Dist: imblearn>=0.0; extra == 'replication'
Requires-Dist: lime>=0.2.0.1; extra == 'replication'
Requires-Dist: matplotlib>=3.8.3; extra == 'replication'
Requires-Dist: rich>=13.7.1; extra == 'replication'
Requires-Dist: scikit-learn>=1.4.1.post1; extra == 'replication'
Requires-Dist: scipy>=1.12.0; extra == 'replication'
Requires-Dist: seaborn>=0.13.2; extra == 'replication'
Requires-Dist: statsmodels>=0.14.1; extra == 'replication'
Requires-Dist: tabulate>=0.9.0; extra == 'replication'
Requires-Dist: typer>=0.12.4; extra == 'replication'
Requires-Dist: xgboost>=2.0.3; extra == 'replication'
